aiida_shell/__init__.py
aiida_shell/launch.py
aiida_shell/py.typed
aiida_shell/calculations/__init__.py
aiida_shell/calculations/shell.py
aiida_shell/data/__init__.py
aiida_shell/data/code.py
aiida_shell/data/entry_point.py
aiida_shell/data/pickled.py
aiida_shell/parsers/__init__.py
aiida_shell/parsers/shell.py
aiida_shell-0.8.2.dist-info/entry_points.txt
aiida_shell-0.8.2.dist-info/licenses/LICENSE.txt
aiida_shell-0.8.2.dist-info/WHEEL
aiida_shell-0.8.2.dist-info/METADATA
aiida_shell-0.8.2.dist-info/RECORD
